{"NAME_CONTRACT_TYPE": 0.0, "CODE_GENDER": 0.0, "FLAG_OWN_CAR": 0.0, "FLAG_OWN_REALTY": 1.0, "CNT_CHILDREN": 0.0, "AMT_INCOME_TOTAL": 147150.0, "AMT_CREDIT": 513531.0, "AMT_ANNUITY": 24903.0, "AMT_GOODS_PRICE": 450000.0, "NAME_TYPE_SUITE": 6.0, "NAME_INCOME_TYPE": 7.0, "NAME_EDUCATION_TYPE": 4.0, "NAME_FAMILY_STATUS": 1.0, "NAME_HOUSING_TYPE": 1.0, "REGION_POPULATION_RELATIVE": 0.01885, "DAYS_REGISTRATION": -4504.0, "DAYS_ID_PUBLISH": -3254.0, "FLAG_MOBIL": 1.0, "FLAG_EMP_PHONE": 1.0, "FLAG_WORK_PHONE": 0.0, "FLAG_CONT_MOBILE": 1.0, "FLAG_PHONE": 0.0, "FLAG_EMAIL": 0.0, "OCCUPATION_TYPE": 8.0, "CNT_FAM_MEMBERS": 2.0, "REGION_RATING_CLIENT": 2.0, "REGION_RATING_CLIENT_W_CITY": 2.0, "WEEKDAY_APPR_PROCESS_START": 4.0, "HOUR_APPR_PROCESS_START": 12.0, "REG_REGION_NOT_LIVE_REGION": 0.0, "REG_REGION_NOT_WORK_REGION": 0.0, "LIVE_REGION_NOT_WORK_REGION": 0.0, "REG_CITY_NOT_LIVE_CITY": 0.0, "REG_CITY_NOT_WORK_CITY": 0.0, "LIVE_CITY_NOT_WORK_CITY": 0.0, "ORGANIZATION_TYPE": 33.0, "EXT_SOURCE_1": 0.5059979305057544, "EXT_SOURCE_2": 0.5659614260608526, "EXT_SOURCE_3": 0.5352762504724826, "YEARS_BEGINEXPLUATATION_AVG": 0.9816, "FLOORSMAX_AVG": 0.1667, "YEARS_BEGINEXPLUATATION_MODE": 0.9816, "FLOORSMAX_MODE": 0.1667, "YEARS_BEGINEXPLUATATION_MEDI": 0.9816, "FLOORSMAX_MEDI": 0.1667, "TOTALAREA_MODE": 0.0688, "EMERGENCYSTATE_MODE": 0.0, "OBS_30_CNT_SOCIAL_CIRCLE": 0.0, "DEF_30_CNT_SOCIAL_CIRCLE": 0.0, "OBS_60_CNT_SOCIAL_CIRCLE": 0.0, "DEF_60_CNT_SOCIAL_CIRCLE": 0.0, "DAYS_LAST_PHONE_CHANGE": -757.0, "FLAG_DOCUMENT_2": 0.0, "FLAG_DOCUMENT_3": 1.0, "FLAG_DOCUMENT_4": 0.0, "FLAG_DOCUMENT_5": 0.0, "FLAG_DOCUMENT_6": 0.0, "FLAG_DOCUMENT_7": 0.0, "FLAG_DOCUMENT_8": 0.0, "FLAG_DOCUMENT_9": 0.0, "FLAG_DOCUMENT_10": 0.0, "FLAG_DOCUMENT_11": 0.0, "FLAG_DOCUMENT_12": 0.0, "FLAG_DOCUMENT_13": 0.0, "FLAG_DOCUMENT_14": 0.0, "FLAG_DOCUMENT_15": 0.0, "FLAG_DOCUMENT_16": 0.0, "FLAG_DOCUMENT_17": 0.0, "FLAG_DOCUMENT_18": 0.0, "FLAG_DOCUMENT_19": 0.0, "FLAG_DOCUMENT_20": 0.0, "FLAG_DOCUMENT_21": 0.0, "AMT_REQ_CREDIT_BUREAU_HOUR": 0.0, "AMT_REQ_CREDIT_BUREAU_DAY": 0.0, "AMT_REQ_CREDIT_BUREAU_WEEK": 0.0, "AMT_REQ_CREDIT_BUREAU_MON": 0.0, "AMT_REQ_CREDIT_BUREAU_QRT": 0.0, "AMT_REQ_CREDIT_BUREAU_YEAR": 1.0, "EXT_SOURCE_1_missing": 1.0, "YEARS_BEGINEXPLUATATION_AVG_missing": 0.0, "FLOORSMAX_AVG_missing": 0.0, "YEARS_BEGINEXPLUATATION_MODE_missing": 0.0, "FLOORSMAX_MODE_missing": 0.0, "YEARS_BEGINEXPLUATATION_MEDI_missing": 0.0, "FLOORSMAX_MEDI_missing": 0.0, "TOTALAREA_MODE_missing": 0.0, "OCCUPATION_TYPE_missing": 0.0, "EMERGENCYSTATE_MODE_missing": 0.0, "AGE_YEARS": 43.12, "DAYS_EMPLOYED_anomaly": 0.0, "YEARS_EMPLOYED": 3.32, "CREDIT_INCOME_RATIO": 3.265066666666667, "ANNUITY_INCOME_RATIO": 0.1628333333333333, "CREDIT_TERM": 20.0, "EMPLOYED_LIFE_RATIO": 0.0886349598517603, "INCOME_PER_PERSON": 75000.0, "EXT_SOURCE_MEAN": 0.5215641323920002, "EXT_SOURCE_MIN": 0.4034627418433645, "EXT_SOURCE_WEIGHTED": 0.5261712817325334, "DOCUMENT_FLAGS_SUM": 1.0, "SOCIAL_CIRCLE_DEFAULT_RATE": 0.0}